Metadata-Version: 1.1
Name: testrail-reporter
Version: 0.0.4
Summary: Nosetests Plugin to Report Test Results to TestRail.
Home-page: https://github.com/charlesthomas/testrail_reporter
Author: Charles Thomas
Author-email: ch@rlesthom.as
License: MIT License
